neatest/__init__.py
neatest/__main__.py
neatest/_constants.py
neatest/_neatest.py
neatest-3.9.1.dist-info/LICENSE
neatest-3.9.1.dist-info/METADATA
neatest-3.9.1.dist-info/WHEEL
neatest-3.9.1.dist-info/entry_points.txt
neatest-3.9.1.dist-info/top_level.txt
neatest-3.9.1.dist-info/RECORD
