Metadata-Version: 2.1
Name: neatest
Version: 3.9.1
Summary: Discovers and runs unit tests with a single-word command.
Home-page: https://github.com/rtmigo/neatest_py#neatest
Author: Artёm IG
Author-email: ortemeo@gmail.com
License: MIT
Keywords: unit,tests,unittest,unit-tests,testing,discovery,test,ci
Platform: UNKNOWN
Classifier: Intended Audience :: Developers
Classifier: License :: OSI Approved :: MIT License
Classifier: Topic :: Software Development :: Testing
Classifier: Topic :: Software Development :: Testing :: Unit
Classifier: Topic :: Software Development :: Quality Assurance
Classifier: Programming Language :: Python :: 3.7
Classifier: Programming Language :: Python :: 3.8
Classifier: Programming Language :: Python :: 3.9
Classifier: Programming Language :: Python :: 3.10
Classifier: Operating System :: POSIX
Classifier: Operating System :: Microsoft :: Windows
Requires-Python: >=3.7
License-File: LICENSE
